README.rst
setup.py
codepoints/__init__.py
codepoints.egg-info/PKG-INFO
codepoints.egg-info/SOURCES.txt
codepoints.egg-info/dependency_links.txt
codepoints.egg-info/not-zip-safe
codepoints.egg-info/requires.txt
codepoints.egg-info/top_level.txt