Metadata-Version: 1.1
Name: codepoints
Version: 1.0
Summary: Converts code point sequences to and from Unicode strings
Home-page: https://github.com/bhamiltoncx/pycodepoints/
Author: Ben Hamilton
Author-email: bhamiltoncx@gmail.com
License: BSD
Keywords: unicode utf16 surrogate pair bmp smp astral codepoint codeunit emoji maxunicode
Platform: UNKNOWN
Classifier: Development Status :: 4 - Beta
Classifier: License :: OSI Approved :: BSD License
Classifier: Operating System :: OS Independent
Classifier: Topic :: Software Development :: Internationalization
Classifier: Topic :: Text Processing
Classifier: Programming Language :: Python
Classifier: Programming Language :: Python :: 2
Classifier: Programming Language :: Python :: 2.7
Classifier: Programming Language :: Python :: 3
Classifier: Programming Language :: Python :: 3.5
